kazemlstack/__init__.py
kazemlstack/cli/train_vit_cifar.py
kazemlstack/data/__init__.py
kazemlstack/data/cifar.py
kazemlstack/model/ViT.py
kazemlstack/model/__init__.py
kazemlstack-0.1.0.dist-info/METADATA
kazemlstack-0.1.0.dist-info/WHEEL
kazemlstack-0.1.0.dist-info/RECORD
