Metadata-Version: 2.4
Name: kazemlstack
Version: 0.1.0
Summary: Kaze MLOps stack
Requires-Python: >=3.12
Requires-Dist: bentoml>=1.4.8
Requires-Dist: chex>=0.1.89
Requires-Dist: dagster>=1.10.10
Requires-Dist: fire>=0.7.0
Requires-Dist: flax>=0.10.5
Requires-Dist: grain>=0.2.7
Requires-Dist: jaxtyping>=0.3.1
Requires-Dist: minio>=7.2.15
Requires-Dist: mlflow>=2.21.3
Requires-Dist: optax>=0.2.4
Provides-Extra: cuda
Requires-Dist: jax[cuda]>=0.5.3; extra == 'cuda'
